Metadata-Version: 1.1
Name: MN
Version: 0.0
Summary: Application software.
Home-page: UNKNOWN
Author: pypiContributor
Author-email: UNKNOWN
License: none
Download-URL: https://pypi.org/MN
Platform: OS-independent
Platform: Many
